litemodel/__init__.py
litemodel/async_core.py
litemodel/constants.py
litemodel/core.py
litemodel/pool.py
litemodel/py.typed
litemodel/sql_templates.py
litemodel-0.1.11.dist-info/METADATA
litemodel-0.1.11.dist-info/WHEEL
litemodel-0.1.11.dist-info/RECORD
