Metadata-Version: 2.4
Name: litemodel
Version: 0.1.11
Summary: Lightweight extensible ORM for SQLite
Author-email: Joe Pasquantonio <joe.pasquantonio@gmail.com>
Requires-Python: >=3.11
Requires-Dist: aiosqlite>=0.20.0
Requires-Dist: jinja2>=3.1.4
